rsp/__init__.py
rsp/__main__.py
rsp/asdnotify.py
rsp/baselistener.py
rsp/constants.py
rsp/keygen.py
rsp/ratelimit.py
rsp/sockslistener.py
rsp/ssh_pool.py
rsp/transparentlistener.py
rsp/trust.py
rsp/utils.py
rsp-1.0.1.dist-info/LICENSE
rsp-1.0.1.dist-info/METADATA
rsp-1.0.1.dist-info/WHEEL
rsp-1.0.1.dist-info/entry_points.txt
rsp-1.0.1.dist-info/top_level.txt
rsp-1.0.1.dist-info/zip-safe
rsp-1.0.1.dist-info/RECORD
