Metadata-Version: 2.1
Name: rsp
Version: 1.0.1
Summary: Rapid SSH Proxy
Home-page: https://github.com/Snawoot/rsp
Author: Vladislav Yarmak
Author-email: vladislav-ex-src@vm-0.com
License: MIT
Platform: UNKNOWN
Classifier: Programming Language :: Python :: 3.5
Classifier: License :: OSI Approved :: MIT License
Classifier: Operating System :: OS Independent
Classifier: Development Status :: 4 - Beta
Classifier: Environment :: No Input/Output (Daemon)
Classifier: Intended Audience :: System Administrators
Classifier: Natural Language :: English
Classifier: Topic :: Internet
Classifier: Topic :: Security
Requires-Python: >=3.5.3
Requires-Dist: asyncssh (>=1.16.0)
Provides-Extra: dev
Requires-Dist: setuptools (>=38.6.0) ; extra == 'dev'
Requires-Dist: wheel (>=0.31.0) ; extra == 'dev'
Requires-Dist: twine (>=1.11.0) ; extra == 'dev'
Provides-Extra: uvloop
Requires-Dist: uvloop (>=0.11.0) ; extra == 'uvloop'
